MANIFEST.in
README.txt
setup.py
docs/LICENSE.GPL
docs/LICENSE.txt
medialog/.DS_Store
medialog/__init__.py
medialog.galleryviewlet.egg-info/PKG-INFO
medialog.galleryviewlet.egg-info/SOURCES.txt
medialog.galleryviewlet.egg-info/dependency_links.txt
medialog.galleryviewlet.egg-info/entry_points.txt
medialog.galleryviewlet.egg-info/namespace_packages.txt
medialog.galleryviewlet.egg-info/not-zip-safe
medialog.galleryviewlet.egg-info/requires.txt
medialog.galleryviewlet.egg-info/top_level.txt
medialog/galleryviewlet/.DS_Store
medialog/galleryviewlet/README.txt
medialog/galleryviewlet/__init__.py
medialog/galleryviewlet/config.py
medialog/galleryviewlet/configure.zcml
medialog/galleryviewlet/interfaces.py
medialog/galleryviewlet/settings.py
medialog/galleryviewlet/testing.py
medialog/galleryviewlet/vocabularies.py
medialog/galleryviewlet/browser/__init__.py
medialog/galleryviewlet/browser/configure.zcml
medialog/galleryviewlet/browser/forms.py
medialog/galleryviewlet/browser/galleryviewlet.pt
medialog/galleryviewlet/browser/galleryviewlet_below.pt
medialog/galleryviewlet/browser/interfaces.py
medialog/galleryviewlet/browser/utils.py
medialog/galleryviewlet/browser/viewgallery.pt
medialog/galleryviewlet/browser/viewlets.py
medialog/galleryviewlet/profiles/.DS_Store
medialog/galleryviewlet/profiles/default/actions.xml
medialog/galleryviewlet/profiles/default/browserlayer.xml
medialog/galleryviewlet/profiles/default/metadata.xml
medialog/galleryviewlet/profiles/default/viewlets.xml
medialog/galleryviewlet/tests/__init__.py
medialog/galleryviewlet/tests/base.py
medialog/galleryviewlet/tests/test_doctest.py
medialog/galleryviewlet/tests/test_example.py