Metadata-Version: 1.1
Name: medialog.galleryviewlet
Version: 0.4.1
Summary: Adds a viewlet to display a truegallery whereever you want
Home-page: https://github.com/collective/medialog.galleryviewlet
Author: Espen Moe-Nilssen
Author-email: espen@medialog.no
License: gpl
Platform: UNKNOWN
Classifier: Framework :: Plone
Classifier: Intended Audience :: Developers
Classifier: Operating System :: OS Independent
Classifier: Programming Language :: Python
Classifier: Topic :: Software Development
Classifier: Framework :: Plone
Classifier: Framework :: Plone :: 4.1
Classifier: Framework :: Plone :: 4.2
